cfprefsmon/__init__.py
cfprefsmon/__main__.py
cfprefsmon/_version.py
cfprefsmon-2.0.0.dist-info/licenses/LICENSE
cfprefsmon-2.0.0.dist-info/METADATA
cfprefsmon-2.0.0.dist-info/WHEEL
cfprefsmon-2.0.0.dist-info/entry_points.txt
cfprefsmon-2.0.0.dist-info/top_level.txt
cfprefsmon-2.0.0.dist-info/RECORD
