Metadata-Version: 2.4
Name: cfprefsmon
Version: 2.0.0
Summary: Search for interesting internal preferences inside a connected iDevice
Author-email: doronz88 <doron88@gmail.com>
Maintainer-email: doronz88 <doron88@gmail.com>
License:                     GNU GENERAL PUBLIC LICENSE
Project-URL: Homepage, https://github.com/doronz88/cfprefsmon
Project-URL: Bug Reports, https://github.com/doronz88/cfprefsmon/issues
Keywords: ios,cli,preferences,cfprefsd,monitor
Classifier: Development Status :: 5 - Production/Stable
Classifier: License :: OSI Approved :: GNU General Public License v3 or later (GPLv3+)
Classifier: Programming Language :: Python :: 3
Classifier: Programming Language :: Python :: 3.9
Classifier: Programming Language :: Python :: 3.10
Classifier: Programming Language :: Python :: 3.11
Classifier: Programming Language :: Python :: 3.12
Classifier: Programming Language :: Python :: 3.13
Classifier: Programming Language :: Python :: 3.14
Classifier: Programming Language :: Python :: 3 :: Only
Requires-Python: >=3.9
License-File: LICENSE
Requires-Dist: pymobiledevice3>=7.0.7
Requires-Dist: maclog
Requires-Dist: typer
Dynamic: license-file
